{
  "entries": [
    {
      "location": "Test  1",
      "comments": "fffff",
      "type": "Service",
      "startTime": "2022-09-29T16:00:00.149Z",
      "endTime": "2022-09-29T16:00:00.149Z",
      "userId": 1,
      "id": 1
    },
    {
      "location": "Tetrsrt",
      "comments": "rwerwer",
      "type": "Service",
      "startTime": "2022-09-29T16:00:00.945Z",
      "endTime": "2022-09-29T16:00:00.945Z",
      "userId": 1,
      "id": 2
    },
    {
      "location": "Test",
      "comments": "kara",
      "type": "Testing",
      "startTime": "2022-09-29T16:00:00.935Z",
      "endTime": "2022-09-29T16:00:00.935Z",
      "userId": 2,
      "id": 3
    },
    {
      "location": "Did it Dif?",
      "comments": "ffffff",
      "type": "Service",
      "startTime": "2022-09-29T16:00:00.176Z",
      "endTime": "2022-09-29T16:00:00.176Z",
      "userId": 3,
      "id": 4
    },
    {
      "id": 5,
      "location": "Third One",
      "comments": "Found IT!!!!!!",
      "type": "Testing",
      "startTime": "2022-09-27T16:00:00.000Z",
      "endTime": "2022-09-27T16:00:00.000Z",
      "userId": 1
    },
    {
      "location": "Tester",
      "comments": "fasdfdsf",
      "type": "Service",
      "startTime": "2022-09-29T16:00:00.446Z",
      "endTime": "2022-09-29T16:00:00.446Z",
      "userId": 3,
      "id": 6
    }
  ],
  "expenses": [
    {
      "date": "2022-09-29T04:00:00.000Z",
      "destination": "numba 5",
      "miles": 10,
      "userId": 1,
      "id": 1
    },
    {
      "date": "2022-09-12T04:00:00.000Z",
      "destination": "Second 2",
      "miles": 88,
      "userId": 1,
      "id": 2
    },
    {
      "date": "2022-09-29T04:00:00.000Z",
      "destination": "Mark 1",
      "miles": 12,
      "userId": 3,
      "id": 3
    },
    {
      "date": "2022-09-29T04:00:00.000Z",
      "destination": "Kara 2",
      "miles": 899,
      "userId": 2,
      "id": 4
    },
    {
      "date": "2022-09-29T04:00:00.000Z",
      "destination": "Mark 2",
      "miles": 10,
      "userId": 3,
      "id": 5
    },
    {
      "date": "2022-09-29T04:00:00.000Z",
      "destination": "Another Kara",
      "miles": 10,
      "userId": 2,
      "id": 6
    },
    {
      "date": "2022-09-29T04:00:00.000Z",
      "destination": "fasdfasdf",
      "miles": 10,
      "userId": 1,
      "id": 7
    },
    {
      "date": "2022-09-28T04:00:00.000Z",
      "destination": "fasddsf",
      "miles": 78,
      "userId": 2,
      "id": 8
    }
  ],
  "users": [
    {
      "id": 1,
      "username": "kraighebert@gmail.com",
      "password": "password",
      "firstName": "Kraig",
      "lastName": "Hebert",
      "isAdmin": true,
      "hasCellPhone": true
    },
    {
      "id": 2,
      "username": "karacanata@gmail.com",
      "password": "password",
      "firstName": "Kara",
      "lastName": "Canata",
      "isAdmin": false,
      "hasCellPhone": false
    },
    {
      "id": 3,
      "username": "marksmith@gmail.com",
      "password": "password",
      "firstName": "Mark",
      "lastName": "Smith",
      "isAdmin": true,
      "hasCellPhone": false
    }
  ]
}